noapi/Item.py
noapi/Item.pyi
noapi/Link.py
noapi/Link.pyi
noapi/List.py
noapi/List.pyi
noapi/Property.py
noapi/Property.pyi
noapi/Slice.py
noapi/Slice.pyi
noapi/__init__.py
noapi/__init__.pyi
noapi/__main__.py
noapi/__main__.pyi
noapi/_version.py
noapi/asyn.py
noapi/await_async.py
noapi/await_async.pyi
noapi/datanet.py
noapi/datatypes.py
noapi/device-raspi.py
noapi/device-raspi.pyi
noapi/device-stm32.py
noapi/device-stm32.pyi
noapi/dsmethodprop.py
noapi/main.py
noapi/msg.py
noapi/msg.pyi
noapi/py.typed
noapi/pyarmor_runtime_002916/__init__.py
noapi/pyarmor_runtime_002916/pyarmor_runtime.so
no_api_sdk-0.1.22.dist-info/METADATA
no_api_sdk-0.1.22.dist-info/WHEEL
no_api_sdk-0.1.22.dist-info/top_level.txt
no_api_sdk-0.1.22.dist-info/RECORD
