Metadata-Version: 2.1
Name: no-api-sdk
Version: 0.1.22
Summary: no-api python sdk
Home-page: https://no-api.net/
Author: no-api.net
Author-email: info@no-api.net
Classifier: Programming Language :: Python :: 3
Classifier: License :: Other/Proprietary License
Classifier: Operating System :: OS Independent
Requires-Python: >=3.8
Requires-Dist: websockets>=11
Requires-Dist: nest-asyncio>=1.5
Requires-Dist: typing-extensions>=4.7
